toptenticle/__init__.py
toptenticle/setup.py
toptenticle-1.0.0.dist-info/METADATA
toptenticle-1.0.0.dist-info/WHEEL
toptenticle-1.0.0.dist-info/top_level.txt
toptenticle-1.0.0.dist-info/RECORD
