Metadata-Version: 2.1
Name: toptenticle
Version: 1.0.0
Summary: Simple!
Home-page: UNKNOWN
Author: GoodWorks Soft Co.
Author-email: <tylerfromgw@gmail.com>
License: UNKNOWN
Keywords: top ten maker,csvtools
Platform: UNKNOWN
Classifier: Development Status :: 1 - Planning
Classifier: Intended Audience :: Developers
Classifier: Programming Language :: Python :: 3
Requires-Dist: pibrella
